{
  "$schema": "https://biomejs.dev/schemas/2.1.1/schema.json",
  "vcs": {
    "enabled": false,
    "clientKind": "git",
    "useIgnoreFile": false,
    "defaultBranch": "main"
  },
  "extends": ["@tutods/biome-config"],
  "files": {
    "includes": ["**", "!**/packages/**/package.json", "!**/config/**/package.json", "!.nx", "!**/dist"]
  },
  "linter": {
    "rules": {
      "style": {
        "noParameterAssign": "error",
        "useAsConstAssertion": "error",
        "useDefaultParameterLast": "error",
        "useEnumInitializers": "error",
        "useSelfClosingElements": "error",
        "useSingleVarDeclarator": "error",
        "noUnusedTemplateLiteral": "error",
        "useNumberNamespace": "error",
        "noInferrableTypes": "error",
        "noUselessElse": "error"
      }
    }
  }
}
